pytest_param.py
pytest_param-0.1.1.dist-info/DESCRIPTION.rst
pytest_param-0.1.1.dist-info/METADATA
pytest_param-0.1.1.dist-info/RECORD
pytest_param-0.1.1.dist-info/WHEEL
pytest_param-0.1.1.dist-info/entry_points.txt
pytest_param-0.1.1.dist-info/metadata.json
pytest_param-0.1.1.dist-info/top_level.txt
